getostheme/__init__.py
getostheme/__main__.py
getostheme-2024.0.1.dist-info/entry_points.txt
getostheme-2024.0.1.dist-info/LICENSE.md
getostheme-2024.0.1.dist-info/METADATA
getostheme-2024.0.1.dist-info/WHEEL
getostheme-2024.0.1.dist-info/RECORD
