Metadata-Version: 2.1
Name: getostheme
Version: 2024.0.1
Summary: Use this module to get the OS theme (dark/light)
Home-page: https://github.com/FredHappyface/Python.GetOSTheme
License: MIT
Author: FredHappyface
Requires-Python: >=3.8,<4.0
Classifier: Development Status :: 5 - Production/Stable
Classifier: Environment :: Console
Classifier: Intended Audience :: Developers
Classifier: Intended Audience :: Education
Classifier: License :: OSI Approved :: MIT License
Classifier: Natural Language :: English
Classifier: Operating System :: OS Independent
Classifier: Programming Language :: Python :: 3
Classifier: Programming Language :: Python :: 3.8
Classifier: Programming Language :: Python :: 3.9
Classifier: Programming Language :: Python :: 3.10
Classifier: Programming Language :: Python :: 3.11
Classifier: Programming Language :: Python :: 3.12
Classifier: Programming Language :: Python :: Implementation :: CPython
Classifier: Topic :: Software Development :: Libraries :: Python Modules
Classifier: Topic :: Utilities
Provides-Extra: qt
Requires-Dist: PyQt5 (>=5.15.10,<6) ; extra == "qt"
Project-URL: Documentation, https://github.com/FredHappyface/Python.GetOSTheme/blob/master/README.md
Project-URL: Repository, https://github.com/FredHappyface/Python.GetOSTheme
